{"title":"Mobilfunksendeanlagen",
"subtitle":"",
"kuerzel":"I.02.16.04296",
"kuerzelKunde":"1204",
"description":"Mobilfunksendeanlagen",
"id":4296,
"thema":"02 Raum, Umwelt",
"unterthema":"Nichtionisierende Strahlung",
"kennzahlenset":"Umwelt",
"raeumlicheGliederung":["Kanton"],
"aktualisierungsdatum":"",
"schlagwort":["Nichtionisierende Strahlung"],
"stufe1":"Nichtionisierende Strahlung",
"stufe2":"",
"stufe3":"",
"stufe4":"",
"stufe5":"", 
"lesehilfe":"",
"erlaeuterungen":"Anzahl der sich in Betrieb befindenden Mobilfunksendeanlagen, unterteilt nach Sendeleistung. Die Anzahl Antennen pro Standort ist unterschiedlich, wird jedoch für den Indikator nicht berücksichtigt.<br><br>Neue Anlagen sowie Umbauten bestehender Anlagen sind in der Regel bewilligungspflichtig, wodurch die Daten im Rahmen des Baubewilligungsverfahrens vom zuständigen Bauinspektorat erfasst und dem Lufthygieneamt beider Basel gemeldet werden. Spezielle Fälle (geringfügige Änderungen oder Anlagen mit sehr kleinen Sendeleistungen (maximal 6 Watt ERP)) sind nur meldepflichtig, diese Daten werden dem Lufthygieneamt beider Basel direkt von den Betreibern gemeldet.",
"template":"dotplot",
"option":"options001",
"visible":true,
"visibleInPortal":true,
"parentId":null,
"children":[],
"renderLink":[],
"quellenangabe":["Lufthygieneamt beider Basel"],
"externalLinks":["www.umweltbericht.bs-bl.ch/indikatoren-12-1204"]
}
