{"title":"Siedlungserneuerung",
"subtitle":"in Verdichtungsgrad (neuerstellte/abgebrochene Wohnungen)",
"kuerzel":"I.09.1.4317",
"kuerzelKunde":"0904",
"description":"Siedlungserneuerung",
"id":4317,
"thema":"09 Bau-, Wohnungswesen",
"unterthema":"Gebäude und Wohnungen",
"kennzahlenset":"Umwelt",
"raeumlicheGliederung":["Kanton"],
"aktualisierungsdatum":"2020-10-06T10:00:47.4747",
"stufe1":"Thema Landschaft",
"stufe2":"",
"stufe3":"",
"stufe4":"",
"stufe5":"", 
"lesehilfe":"<Bitte Kommentar erfassen>",
"erlaeuterungen":"Als Wohnersatzprojekt gelten Projekte, bei welchen ältere Wohnbauten abgebrochen und durch neue Wohngebäude ersetzt werden. Zur Ermittlung der Wohnersatzprojekte wird um abgerissene Wohngebäude ein Puffer von 20 Metern gelegt. Für die neuen Wohngebäude, die in den Folgejahren (bis zu fünf Jahre) innerhalb dieses Puffers gebaut werden, wird das Verhältnis der alten zur neuen Wohnungsanzahl berechnet. Als Datengrundlage dient die Gebäudedatenbank des Kantons Basel-Landschaft.<br><br>Verhältnis zwischen abgebrochenen und neu erstellten Wohnungen durch Siedlungserneuerung (Wohnersatzprojekte). Der Indikator zeigt somit den Grad der Verdichtung, welcher durch die Siedlungserneuerung erreicht wird.",
"template":"map_gemeinden",
"darstellungsart":"",
"printformat":"", 
"visible":false,
"visibleInPortal":true,
"orderKey":"09_00_00_00_00_000",
"parentId":null,
"children":[],
"renderLink":[],
"quellenangabe":[],
"datenInChartIntegriert":true,
"externalLinks":["Weitere Informationen zum Indikator: <a href = 'http://www.umweltberichtbeiderbasel.bs.ch/indikatoren-09-0904' target = '_blank'>Umweltbericht beider Basel</a>"],
"data-id":4317, 
"chart-id":4317, 
"filter":""
}
