{"title":"Median des Reinvermögens",
"subtitle":"in Franken, Basel-Stadt, 2007 und 2016",
"kuerzel":"I.18.2.06905",
"kuerzelKunde":"2-8",
"description":"Median des Reinvermögens",
"id":6905,
"thema":"18 Öffentliche Finanzen",
"unterthema":"Steuern",
"kennzahlenset":"Steuern",
"raeumlicheGliederung":["Kanton"],
"aktualisierungsdatum":"2019-06-04T11:06:30.3030",
"stufe1":"Ordentliche Veranlagung natürlicher Personen",
"stufe2":"",
"stufe3":"",
"stufe4":"",
"stufe5":"", 
"lesehilfe":"Der höchste Median des Reinvermögens 2016 wird mit rund 100 000 Franken in der Einwohnergemeinde Bettingen verzeichnet. Bereits 2007 war in Bettingen der höchste Median zu beobachten.",
"erlaeuterungen":"Grundlage der Auswertungen sind die Veranlagungen von ganzjährig in Basel-Stadt steuerpflichtigen Personen; ohne Auswärtige und ohne Wochenaufenthalter.",
"template":"line001",
"darstellungsart":"Grafik",
"printformat":"", 
"visible":true,
"visibleInPortal":true,
"orderKey":"02_00_00_00_00_008",
"parentId":null,
"children":[],
"renderLink":[],
"quellenangabe":["Steuerstatistik Basel-Stadt"],
"datenInChartIntegriert":false,
"externalLinks":[""],
"data-id":6905, 
"chart-id":6905, 
"filter":""
}
