{"id":8069,
"parentId":null,
"children":["8639"],
"template":"line001",
"title":"Anteil an der Gesamtbeschäftigung der Stadt Basel",
"subtitle":"Wohnviertel Klybeck und Kleinhüningen",
"kennzahlenset":"Stadtteilmonitoring Klybeck-Kleinhüningen",
"kuerzel":"I.03.2.07688",
"kuerzelKunde":"3.01",
"description":"Anteil an der Gesamtbeschäftigung der Stadt Basel",
"thema":"03 Arbeit, Erwerb",
"unterthema":"Beschäftigte ",
"raeumlicheGliederung":["Wohnviertel"],
"aktualisierungsdatum":"2021-04-26T09:04:27.2727",
"stufe1":"3 Erwerbsleben und Steuern",
"stufe2":"",
"stufe3":"",
"stufe4":"",
"stufe5":"", 
"lesehilfe":"Im Jahr 2018 sind in der Stadt Basel 185 432 Beschäftigte tätig. Davon arbeiten 4 089 im Wohnviertel Klybeck und 7 468 im Wohnviertel Kleinhüningen. Anteilsmässig sind dies 2,2% bzw. 4,0%. Insgesamt entfallen somit 6,2% der Beschäftigung der Stadt Basel auf den Stadtteil Klybeck-Kleinhüningen.",
"erlaeuterungen":"Als Beschäftigte gelten Personen, die eine Tätigkeit ausüben, und die einen AHV-pflichtigen Lohn von mindestens 2 300 Franken pro Jahr erhalten. Die Referenzperiode ist jeweils der Dezember des Jahres.",
"darstellungsart":"",
"printformat":"", 
"visible":true,
"visibleInPortal":true,
"orderKey":"03_00_00_00_00_001",
"renderLink":[],
"quellenangabe":["Bundesamt für Statistik (BFS), Statistik der Unternehmensstruktur (STATENT)"],
"datenInChartIntegriert":false,
"externalLinks":[""],
"data-id":8069, 
"chart-id":8069, 
"filter":""
}
