{"id":8104,
"parentId":7961,
"children":[],
"template":"template001_print",
"title":"Anteil der Privathaushalte mit minderjährigen Kindern",
"subtitle":"2018",
"kennzahlenset":"City-Statistics (Print)",
"kuerzel":"I.01.2.08104",
"kuerzelKunde":"3.1",
"description":"Anteil der Privathaushalte mit minderjährigen Kindern",
"thema":"01 Bevölkerung",
"unterthema":"Haushalte",
"raeumlicheGliederung":["Agglomeration"],
"aktualisierungsdatum":"2021-02-08T08:45:34.3434",
"stufe1":"3. Familienhaushalte und Bildung",
"stufe2":"",
"stufe3":"",
"stufe4":"",
"stufe5":"", 
"lesehilfe":"Der Anteil der Privathaushalte mit Kindern unter 18 Jahren beträgt in der Agglomeration Basel 25,2%. Über alle Agglomerationen verglichen ist der Anteil in den deutschen Gemeinden (34,3%) am höchsten. In jeder Agglomeration ist der Anteil der Privathaushalte mit minderjährigen Kindern in der Kernstadt kleiner als in den jeweiligen übrigen Agglomerationsgemeinden.",
"erlaeuterungen":"Privathaushalte sind alle Haushalte ausser Kollektivhaushalte (z. B. Alters- und Pflegeheime).",
"darstellungsart":"Diagramm",
"printformat":"", 
"visible":true,
"visibleInPortal":false,
"orderKey":"99_00_00_00_00_008",
"renderLink":[],
"quellenangabe":["Bundesamt für Statistik (BFS), City Statistics"],
"datenInChartIntegriert":false,
"externalLinks":[""],
"data-id":8104, 
"chart-id":8104, 
"filter":""
}
