{"title":"Haushalte mit reinen Prämienverbilligungen nach Staatsangehörigkeit",
"subtitle":"Basel-Stadt",
"kuerzel":"I.13.2.08336",
"kuerzelKunde":"1-14",
"description":"Haushalte mit reinen Prämienverbilligungen nach Staatsangehörigkeit",
"id":8336,
"thema":"13 Soziale Sicherheit",
"unterthema":"Sozialleistungen",
"kennzahlenset":"CMS Kennzahlen Soziales",
"raeumlicheGliederung":["Kanton"],
"aktualisierungsdatum":"2020-06-22T18:20:39.3939",
"stufe1":"Prävention und Bekämpfung von Armut",
"stufe2":"1.2 Existenzsicherung",
"stufe3":"",
"stufe4":"",
"stufe5":"", 
"lesehilfe":"Von den 16&nbsp249 Haushalten, die Ende 2019 reine Prämienverbilligungen beziehen, handelt es sich um 9&nbsp034 rein schweizerische und 5&nbsp895 rein ausländische Haushalte. 1&nbsp320 Haushalte bestehen aus Personen mit sowohl schweizerischer als auch ausländischer Staatsangehörigkeit.",
"erlaeuterungen":"Es werden alle Haushalte mit mindestens einer Person mit reinen Prämienverbilligungen (d.&nbsph. ohne Bezügerinnen und Bezüger von Ergänzungsleistungen und Sozialhilfe) gezählt.",
"template":"befragungenProzent001",
"darstellungsart":"Grafik",
"printformat":"", 
"visible":true,
"visibleInPortal":true,
"orderKey":"01_02_00_00_00_114",
"parentId":null,
"children":["8607"],
"renderLink":[],
"quellenangabe":["Basler Informationssystem Sozialleistungen (BISS)"],
"datenInChartIntegriert":false,
"externalLinks":[""],
"data-id":8336, 
"chart-id":8336, 
"filter":""
}
