{"id":9233,
"parentId":9220,
"children":[],
"template":"line001_print",
"title":"Arbeitslose und Arbeitslosenquote in der Branche Nahrungsmittelindustrie",
"subtitle":"Basel-Stadt",
"kennzahlenset":"Arbeitsmarkt (Print)",
"kuerzel":"I.03.4.09233",
"kuerzelKunde":"4.1-02",
"description":"Arbeitslose und Arbeitslosenquote in der Branche Nahrungsmittelindustrie",
"thema":"03 Arbeit, Erwerb",
"unterthema":"Arbeitslose ",
"raeumlicheGliederung":["Kanton"],
"aktualisierungsdatum":"2021-04-09T07:41:29.2929",
"stufe1":"4 Fokusbranchen der Tripartiten Kommission",
"stufe2":"4.1 Nahrungsmittelindustrie",
"stufe3":"",
"stufe4":"",
"stufe5":"", 
"lesehilfe":"Die Zahl der Arbeitslosen in der Nahrungsmittelindustrie ist in den letzten Jahren gestiegen und liegt im Dezember 2020 bei 76. Die mittlere jährliche Arbeitslosenquote liegt 2020 bei 10,1%.",
"erlaeuterungen":"",
"darstellungsart":"",
"printformat":"", 
"visible":true,
"visibleInPortal":false,
"orderKey":"03_01_00_00_00_102",
"renderLink":[],
"quellenangabe":["Staatssekretariat für Wirtschaft SECO, Arbeitslosenstatistik"],
"datenInChartIntegriert":false,
"externalLinks":[""],
"data-id":9233, 
"chart-id":9233, 
"filter":""
}
