{"id":9482,"template":"map_gemeinden_print","data-id":9482,"chart-id":9482,"filter":"","parentId":"9407","children":[],"title":"Jugendquotient nach Gemeinde","subtitle":"trinationale Agglomeration Basel, 2021","lesehilfe":"Die Anzahl Jugendlicher pro 100 Personen zwischen 20 und 64 Jahren ist in den Gemeinden der grenzüberschreitenden Agglomeration Basel mit 24 in Augst und Hemmiken (Schweiz) am tiefsten; mit 54 ist sie in Vieux-Ferrette (Frankreich) am höchsten. Die Quotienten sind in den meisten Gemeinden in Frankreich höher als in der Schweiz und in Deutschland. Den höchsten Jugendquotienten in der Schweiz weist Zullwil auf (43), in Deutschland Rümmingen (40). In der Kernstadt Basel leben 26 Jugendliche pro 100 20- bis 64-Jährige.","erlaeuterungen":"Der Jugendquotient beschreibt das Verhältnis der Personen im Alter von 19 oder weniger Jahren zu jenen im erwerbsfähigen Alter zwischen 20 und 64 Jahren. Das Verhältnis wird pro 100 Personen zwischen 20 und 64 Jahren ausgewiesen.","quellenangabe":["Bundesamt für Statistik (BFS), City Statistics"],"externalLinks":[],"renderLink":[],"raeumlicheGliederung":["Kanton"],"description":"Jugendquotient nach Gemeinde","thema":"01 Bevölkerung","unterthema":"Bestand und Struktur","kuerzel":"I.01.1.09482","kennzahlenset":"City-Statistics (Print)","kuerzelKunde":"2.6","stufe1":"2. Bevölkerungsstruktur","stufe2":"","stufe3":"","stufe4":"","stufe5":"","orderKey":"99_00_00_00_00_007","darstellungsart":"Karte","printformat":"","visible":true,"visibleInPortal":false,"datenInChartIntegriert":false,"aktualisierungsdatum":"2024-01-08T08:58:29"}
