{"id":9581,"template":"line001","data-id":9581,"chart-id":9581,"filter":"","parentId":null,"children":[],"title":"Wohnbevölkerung","subtitle":"Basel-Stadt und Innenstadt","lesehilfe":"In der Innenstadt leben im Jahr 2023 14 517 Menschen. Dies sind 12,4% mehr als 2008. Im Kanton Basel-Stadt wuchs die Einwohnerzahl in diesem Zeitraum um 9,0% auf 206 308.","erlaeuterungen":"Bevölkerungsbestand am Jahresende.","quellenangabe":["Statistisches Amt Basel-Stadt, Bevölkerungsstatistik"],"externalLinks":[],"renderLink":[],"raeumlicheGliederung":["Kanton", "Innenstadt"],"description":"Wohnbevölkerung","thema":"01 Bevölkerung","unterthema":"Bestand und Struktur","kuerzel":"I.01.1.09581","kennzahlenset":"Innenstadt-QuiZ","kuerzelKunde":"2.1-1 ","stufe1":"Ziel 2: Finanzkraft des Kantons Basel-Stadt stärken","stufe2":"","stufe3":"","stufe4":"","stufe5":"","orderKey":"02_00_00_00_00_211","darstellungsart":"","printformat":"","visible":true,"visibleInPortal":true,"datenInChartIntegriert":false,"aktualisierungsdatum":"2024-05-02T08:42:48"}
