{
  "series": [
    {
      "color": "#fabd24",
      "legendIndex": 2,
      "data": [
        [
          "0",
          44
        ],
        [
          "1",
          40.3
        ],
        [
          "2",
          42.5
        ],
        [
          "3",
          42.6
        ],
        [
          "4",
          40.3
        ],
        [
          "5",
          40.7
        ],
        [
          "6",
          38.7
        ],
        [
          "7",
          38
        ],
        [
          "8",
          36.7
        ],
        [
          "9",
          35.4
        ],
        [
          "10",
          33.7
        ],
        [
          "11",
          36.6
        ],
        [
          "12",
          38.2
        ],
        [
          "13",
          36.9
        ],
        [
          "14",
          39.4
        ],
        [
          "15",
          39.1
        ],
        [
          "16",
          40.8
        ],
        [
          "17",
          41
        ],
        [
          "18",
          36.4
        ],
        [
          "19",
          38.6
        ],
        [
          "20",
          38.8
        ],
        [
          "21",
          36.7
        ],
        [
          "22",
          37.2
        ],
        [
          "23",
          39
        ],
        [
          "24",
          38.4
        ],
        [
          "25",
          36.5
        ],
        [
          "26",
          37.8
        ],
        [
          "27",
          36.2
        ],
        [
          "28",
          35.8
        ],
        [
          "29",
          36.2
        ],
        [
          "30",
          36.4
        ],
        [
          "31",
          37
        ],
        [
          "32",
          36.6
        ],
        [
          "33",
          35.5
        ],
        [
          "34",
          33.9
        ],
        [
          "35",
          36.5
        ],
        [
          "36",
          34.4
        ],
        [
          "37",
          34.7
        ],
        [
          "38",
          32.3
        ],
        [
          "39",
          32.6
        ],
        [
          "40",
          30.9
        ],
        [
          "41",
          32.3
        ],
        [
          "42",
          32
        ],
        [
          "43",
          30.2
        ],
        [
          "44",
          29.3
        ],
        [
          "45",
          29.2
        ],
        [
          "46",
          26.9
        ],
        [
          "47",
          27.8
        ],
        [
          "48",
          27.5
        ],
        [
          "49",
          28.3
        ],
        [
          "50",
          26.3
        ],
        [
          "51",
          24.7
        ],
        [
          "52",
          22.2
        ],
        [
          "53",
          23.3
        ],
        [
          "54",
          22.5
        ],
        [
          "55",
          22.7
        ],
        [
          "56",
          21.3
        ],
        [
          "57",
          24.6
        ],
        [
          "58",
          22.1
        ],
        [
          "59",
          22.5
        ],
        [
          "60",
          19.8
        ],
        [
          "61",
          17.2
        ],
        [
          "62",
          16.5
        ],
        [
          "63",
          14.9
        ],
        [
          "64",
          12.7
        ],
        [
          "65",
          11.4
        ],
        [
          "66",
          10
        ],
        [
          "67",
          9
        ],
        [
          "68",
          9.2
        ],
        [
          "69",
          6.9
        ],
        [
          "70",
          7.7
        ],
        [
          "71",
          6.2
        ],
        [
          "72",
          5.3
        ],
        [
          "73",
          5.6
        ],
        [
          "74",
          6
        ],
        [
          "75",
          4.1
        ],
        [
          "76",
          5.1
        ],
        [
          "77",
          4.2
        ],
        [
          "78",
          4.4
        ],
        [
          "79",
          2.4
        ],
        [
          "80",
          1.5
        ],
        [
          "81",
          2.1
        ],
        [
          "82",
          3.5
        ],
        [
          "83",
          3.9
        ],
        [
          "84",
          2.8
        ],
        [
          "85",
          2.9
        ],
        [
          "86",
          2.3
        ],
        [
          "87",
          2.8
        ],
        [
          "88",
          2.2
        ],
        [
          "89",
          3.8
        ],
        [
          "90",
          3.4
        ],
        [
          "91",
          3.6
        ],
        [
          "92",
          2.3
        ],
        [
          "93",
          2.5
        ],
        [
          "94",
          5.7
        ],
        [
          "95",
          4.2
        ],
        [
          "96",
          1.1
        ],
        [
          "97",
          1.8
        ],
        [
          "98",
          0
        ],
        [
          "99",
          0
        ],
        [
          "\u003E99",
          0
        ]
      ],
      "name": "1997",
      "turboThreshold": 0
    },
    {
      "color": "#672773",
      "legendIndex": 2,
      "data": [
        [
          "0",
          41.1
        ],
        [
          "1",
          43.8
        ],
        [
          "2",
          44.1
        ],
        [
          "3",
          41.9
        ],
        [
          "4",
          44.2
        ],
        [
          "5",
          41.6
        ],
        [
          "6",
          42.3
        ],
        [
          "7",
          41.1
        ],
        [
          "8",
          39.5
        ],
        [
          "9",
          39.8
        ],
        [
          "10",
          35.5
        ],
        [
          "11",
          36
        ],
        [
          "12",
          37
        ],
        [
          "13",
          33.9
        ],
        [
          "14",
          32.5
        ],
        [
          "15",
          33.3
        ],
        [
          "16",
          32.5
        ],
        [
          "17",
          31.3
        ],
        [
          "18",
          30.6
        ],
        [
          "19",
          28.7
        ],
        [
          "20",
          29.5
        ],
        [
          "21",
          30.2
        ],
        [
          "22",
          31.1
        ],
        [
          "23",
          35.2
        ],
        [
          "24",
          37.4
        ],
        [
          "25",
          41.4
        ],
        [
          "26",
          44.3
        ],
        [
          "27",
          45.9
        ],
        [
          "28",
          49
        ],
        [
          "29",
          51.2
        ],
        [
          "30",
          51.1
        ],
        [
          "31",
          52.9
        ],
        [
          "32",
          54.8
        ],
        [
          "33",
          51
        ],
        [
          "34",
          49.8
        ],
        [
          "35",
          47.9
        ],
        [
          "36",
          47.2
        ],
        [
          "37",
          45.8
        ],
        [
          "38",
          43.5
        ],
        [
          "39",
          43.2
        ],
        [
          "40",
          41.9
        ],
        [
          "41",
          38.2
        ],
        [
          "42",
          36.9
        ],
        [
          "43",
          35.8
        ],
        [
          "44",
          37.2
        ],
        [
          "45",
          35.6
        ],
        [
          "46",
          33.4
        ],
        [
          "47",
          31.6
        ],
        [
          "48",
          31.2
        ],
        [
          "49",
          29.1
        ],
        [
          "50",
          30.6
        ],
        [
          "51",
          29.6
        ],
        [
          "52",
          28.3
        ],
        [
          "53",
          26.2
        ],
        [
          "54",
          27.3
        ],
        [
          "55",
          25.4
        ],
        [
          "56",
          25.3
        ],
        [
          "57",
          25.9
        ],
        [
          "58",
          25.3
        ],
        [
          "59",
          23.2
        ],
        [
          "60",
          21.9
        ],
        [
          "61",
          19.1
        ],
        [
          "62",
          20.4
        ],
        [
          "63",
          19.2
        ],
        [
          "64",
          19.8
        ],
        [
          "65",
          18
        ],
        [
          "66",
          21.4
        ],
        [
          "67",
          18.9
        ],
        [
          "68",
          18.9
        ],
        [
          "69",
          15.7
        ],
        [
          "70",
          13.7
        ],
        [
          "71",
          13.5
        ],
        [
          "72",
          12.2
        ],
        [
          "73",
          11.4
        ],
        [
          "74",
          9.5
        ],
        [
          "75",
          8.5
        ],
        [
          "76",
          7.7
        ],
        [
          "77",
          7.9
        ],
        [
          "78",
          6
        ],
        [
          "79",
          6.5
        ],
        [
          "80",
          5.4
        ],
        [
          "81",
          5
        ],
        [
          "82",
          5.1
        ],
        [
          "83",
          4.5
        ],
        [
          "84",
          3.3
        ],
        [
          "85",
          4
        ],
        [
          "86",
          4.1
        ],
        [
          "87",
          4.1
        ],
        [
          "88",
          2.4
        ],
        [
          "89",
          1.6
        ],
        [
          "90",
          2.4
        ],
        [
          "91",
          2.5
        ],
        [
          "92",
          3.6
        ],
        [
          "93",
          3.1
        ],
        [
          "94",
          1.7
        ],
        [
          "95",
          0
        ],
        [
          "96",
          3.9
        ],
        [
          "97",
          1.4
        ],
        [
          "98",
          1.6
        ],
        [
          "99",
          0
        ],
        [
          "\u003E99",
          4.6
        ]
      ],
      "name": "2006",
      "turboThreshold": 0
    },
    {
      "color": "#007a2f",
      "legendIndex": 2,
      "data": [
        [
          "0",
          41.9
        ],
        [
          "1",
          41.3
        ],
        [
          "2",
          43.6
        ],
        [
          "3",
          43.1
        ],
        [
          "4",
          42.2
        ],
        [
          "5",
          43.8
        ],
        [
          "6",
          41.7
        ],
        [
          "7",
          40.4
        ],
        [
          "8",
          40.3
        ],
        [
          "9",
          41.4
        ],
        [
          "10",
          38.3
        ],
        [
          "11",
          39.2
        ],
        [
          "12",
          37.2
        ],
        [
          "13",
          34.5
        ],
        [
          "14",
          34.9
        ],
        [
          "15",
          33.8
        ],
        [
          "16",
          34.7
        ],
        [
          "17",
          32.7
        ],
        [
          "18",
          31
        ],
        [
          "19",
          30.1
        ],
        [
          "20",
          26.9
        ],
        [
          "21",
          28.2
        ],
        [
          "22",
          29.5
        ],
        [
          "23",
          29.9
        ],
        [
          "24",
          30.5
        ],
        [
          "25",
          35
        ],
        [
          "26",
          39.4
        ],
        [
          "27",
          42
        ],
        [
          "28",
          43.7
        ],
        [
          "29",
          47.3
        ],
        [
          "30",
          48.9
        ],
        [
          "31",
          51
        ],
        [
          "32",
          52.2
        ],
        [
          "33",
          52.6
        ],
        [
          "34",
          53
        ],
        [
          "35",
          57
        ],
        [
          "36",
          57.2
        ],
        [
          "37",
          55.4
        ],
        [
          "38",
          56.1
        ],
        [
          "39",
          55.7
        ],
        [
          "40",
          54.1
        ],
        [
          "41",
          55.2
        ],
        [
          "42",
          55.2
        ],
        [
          "43",
          51.1
        ],
        [
          "44",
          48.8
        ],
        [
          "45",
          46.8
        ],
        [
          "46",
          46.7
        ],
        [
          "47",
          43.8
        ],
        [
          "48",
          42.5
        ],
        [
          "49",
          41.8
        ],
        [
          "50",
          39.3
        ],
        [
          "51",
          36
        ],
        [
          "52",
          36.3
        ],
        [
          "53",
          33.7
        ],
        [
          "54",
          34.5
        ],
        [
          "55",
          32.1
        ],
        [
          "56",
          30.7
        ],
        [
          "57",
          27.4
        ],
        [
          "58",
          26.9
        ],
        [
          "59",
          26.6
        ],
        [
          "60",
          27.9
        ],
        [
          "61",
          26
        ],
        [
          "62",
          24.9
        ],
        [
          "63",
          24.3
        ],
        [
          "64",
          22.8
        ],
        [
          "65",
          20.2
        ],
        [
          "66",
          20.2
        ],
        [
          "67",
          20.5
        ],
        [
          "68",
          19.8
        ],
        [
          "69",
          18
        ],
        [
          "70",
          17
        ],
        [
          "71",
          15.1
        ],
        [
          "72",
          15.4
        ],
        [
          "73",
          15.4
        ],
        [
          "74",
          15.4
        ],
        [
          "75",
          14.4
        ],
        [
          "76",
          17.4
        ],
        [
          "77",
          14.9
        ],
        [
          "78",
          15.5
        ],
        [
          "79",
          14
        ],
        [
          "80",
          12.2
        ],
        [
          "81",
          12.1
        ],
        [
          "82",
          10.4
        ],
        [
          "83",
          9.5
        ],
        [
          "84",
          7.3
        ],
        [
          "85",
          6.9
        ],
        [
          "86",
          5.4
        ],
        [
          "87",
          7.5
        ],
        [
          "88",
          5.6
        ],
        [
          "89",
          5.2
        ],
        [
          "90",
          4.4
        ],
        [
          "91",
          5
        ],
        [
          "92",
          4.8
        ],
        [
          "93",
          3.1
        ],
        [
          "94",
          1.4
        ],
        [
          "95",
          4.4
        ],
        [
          "96",
          3.7
        ],
        [
          "97",
          2.2
        ],
        [
          "98",
          3.7
        ],
        [
          "99",
          0
        ],
        [
          "\u003E99",
          3.5
        ]
      ],
      "name": "2016",
      "turboThreshold": 0
    }
  ],
  "xAxis": {
    "type": "category",
    "uniqueNames": false,
    "lineColor": "#B9CFD7",
    "lineWidth": 0.5,
    "labels": {
      "style": {
        "color": "#000000",
        "textOverflow": "none"
      },
      "step": 1,
      "rotation": 0
    },
    "tickLength": 0,
    "endOnTick": false,
    "tickInterval": 5
  },
  "chart": {
    "events": {
      "load": function () {
              this.credits.element.onclick = function() {};
              
              //for top-left legends with no x defined: move legend to x position of first yAxis
              if (this['legend']['options']['align'] == 'left' && this['legend']['options']['verticalAlign'] == 'top' && this['legend']['options']['x'] == 0){
                this.update(
                  {
                    legend: {
                      x: this.yAxis[0].left - this.spacingBox.x - this.legend.padding
                    }
                  }
                );
              }              
          }
    },
    "borderColor": "#fbfbfb",
    "backgroundColor": "#fbfbfb",
    "zoomType": "xy",
    "width": 485,
    "height": 428,
    "spacingBottom": 55,
    "style": {
      "fontFamily": "Arial"
    },
    "type": "line",
    "renderTo": "container-6070"
  },
  "title": {
    "style": {
      "fontSize": "14px",
      "fontWeight": "bold",
      "color": "#000000"
    },
    "align": "left",
    "text": "Ausländeranteil nach Alter"
  },
  "subtitle": {
    "style": {
      "fontSize": "12px",
      "fontWeight": "normal",
      "fontFamily": "Arial",
      "color": "#000000"
    },
    "text": "",
    "align": "left"
  },
  "tooltip": {
    "shared": false,
    "headerFormat": "\u003Cspan style=\"font-size: 10px\"\u003E Alter: {point.key}\u003C\u002Fspan\u003E\u003Cbr\u002F\u003E",
    "pointFormat": "\u003Cspan style=\"color:{series.color}\"\u003E●\u003C\u002Fspan\u003E {series.name}: \u003Cb\u003E{point.y}\u003C\u002Fb\u003E%\u003Cbr\u002F\u003E"
  },
  "yAxis": {
    "min": 0,
    "gridLineColor": "#B9CFD7",
    "gridLineWidth": 0.5,
    "title": {
      "style": {
        "color": "#000000",
        "fontSize": null
      },
      "text": null
    },
    "labels": {
      "style": {
        "color": "#000000"
      },
      "format": "{value}%"
    },
    "max": 60
  },
  "credits": {
    "href": "http:\u002F\u002Fwww.statistik.bs.ch",
    "enabled": true,
    "style": {
      "color": "#000000",
      "fontSize": "10px",
      "cursor": "default"
    },
    "position": {
      "align": "left",
      "verticalAlign": "bottom",
      "x": 10,
      "y": -25
    },
    "text": "Quelle: Statistisches Amt Basel-Stadt, Bildungsstatistik\u003Cbr\u002F\u003EZuletzt geändert: 2018-3-21"
  },
  "legend": {
    "enabled": true,
    "layout": "horizontal",
    "verticalAlign": "top",
    "align": "left",
    "symbolRadius": 0,
    "itemWidth": 100,
    "itemMarginBottom": 5,
    "itemStyle": {
      "fontWeight": "normal"
    }
  },
  "plotOptions": {
    "line": {
      "marker": {
        "enabled": false,
        "symbol": "circle"
      }
    }
  },
  "exporting": {
    "filename": 6070
  }
}