{"id":6649,
"parentId":6064,
"children":[],
"template":"populationPyramid001_print",
"title":"Alterspyramide der Schweizerinnen und Schweizer",
"subtitle":"Basel-Stadt, 2003",
"kennzahlenset":"Integration (Print)",
"kuerzel":"I.01.1.06649",
"kuerzelKunde":"A2-4",
"description":"Alterspyramide der Schweizerinnen und Schweizer",
"thema":"01 Bevölkerung",
"unterthema":"Bestand und Struktur",
"raeumlicheGliederung":["Kanton"],
"aktualisierungsdatum":"2023-01-02T08:14:43.4343",
"stufe1":"Kapitel A Bevölkerungsstruktur",
"stufe2":"",
"stufe3":"",
"stufe4":"",
"stufe5":"", 
"lesehilfe":"Bei den älteren Schweizer Staatsangehörigen gibt es 2003 deutlich mehr Frauen als Männer.",
"erlaeuterungen":"Anteil der Fünfjahresklasse des jeweiligen Geschlechts an der gesamten Schweizer Bevölkerung.",
"darstellungsart":"",
"printformat":"", 
"visible":true,
"visibleInPortal":false,
"orderKey":"01_00_00_00_00_204",
"renderLink":[],
"quellenangabe":["Statistisches Amt Basel-Stadt, Bevölkerungsstatistik"],
"datenInChartIntegriert":false,
"externalLinks":[""],
"data-id":6649, 
"chart-id":6649, 
"filter":""
}
